star_chart_spherical_projection/__init__.py
star_chart_spherical_projection/declination_r_axis.py
star_chart_spherical_projection/error_handling.py
star_chart_spherical_projection/generate_star_chart.py
star_chart_spherical_projection/position_of_stars.py
star_chart_spherical_projection/ra_dec_precession_vondrak.py
star_chart_spherical_projection/starClass.py
star_chart_spherical_projection/data/stars_with_data.csv
star_chart_spherical_projection-2.0.1.dist-info/licenses/LICENSE
star_chart_spherical_projection-2.0.1.dist-info/METADATA
star_chart_spherical_projection-2.0.1.dist-info/WHEEL
star_chart_spherical_projection-2.0.1.dist-info/top_level.txt
star_chart_spherical_projection-2.0.1.dist-info/RECORD
