Metadata-Version: 2.4
Name: star-chart-spherical-projection
Version: 2.0.1
Summary: A Python package to generate circular astronomy star charts (past, present, and future) with spherical projection to correct for distortions with more than a hundred named stars accurate over 400,000 years with proper motion and precession of the equinoxes
Author-email: Cora Schneck <cyschneck@gmail.com>
License-Expression: MIT
Project-URL: Issues, https://github.com/cyschneck/Star-Chart-Spherical-Projection/issues
Project-URL: Repository, https://github.com/cyschneck/Star-Chart-Spherical-Projection
Keywords: astronomy,precession,proper motion,python,spherical projection,star charts,stereographic projection
Classifier: Development Status :: 4 - Beta
Classifier: Intended Audience :: Developers
Classifier: Intended Audience :: Education
Classifier: Intended Audience :: Science/Research
Classifier: Programming Language :: Python
Classifier: Programming Language :: Python :: 3 :: Only
Classifier: Programming Language :: Python :: 3.10
Classifier: Programming Language :: Python :: 3.11
Classifier: Programming Language :: Python :: 3.12
Classifier: Programming Language :: Python :: 3.13
Classifier: Topic :: Scientific/Engineering :: Astronomy
Classifier: Topic :: Scientific/Engineering :: Physics
Classifier: Topic :: Scientific/Engineering :: Visualization
Requires-Python: >=3.10
License-File: LICENSE
Requires-Dist: beautifulsoup4
Requires-Dist: matplotlib
Requires-Dist: numpy
Requires-Dist: pandas
Provides-Extra: dev
Requires-Dist: pytest; extra == "dev"
Dynamic: license-file
